Metadata-Version: 1.0
Name: hangmantest
Version: 0.3
Summary: hangmanplayer
Home-page: UNKNOWN
Author: UNKNOWN
Author-email: UNKNOWN
License: UNKNOWN
Platform: UNKNOWN
